profeat/__init__.py
profeat/_libprofeat.cp39-win_amd64.pyd
profeat/_version.py
profeat/.libs/lib_libprof.KFXAA6P4RHMBOQ27ULBG7AFOOGOVIUYP.gfortran-win_amd64.dll
profeat/_libprofeatconfig/__init__.py
profeat/_libprofeatconfig/input-aaindexdb.dat
profeat/_libprofeatconfig/input-ligand.sdf
profeat/_libprofeatconfig/input-param.dat
profeat/_libprofeatconfig/input-pli.dat
profeat/_libprofeatconfig/input-ppi.dat
profeatpy-0.0.2.dist-info/LICENSE
profeatpy-0.0.2.dist-info/METADATA
profeatpy-0.0.2.dist-info/WHEEL
profeatpy-0.0.2.dist-info/top_level.txt
profeatpy-0.0.2.dist-info/RECORD
